{
  "execution_time": "2026-05-26 11:05",
  "ref_tx_id": "20260526-1104",
  "orders": [
    {
      "symbol": "WHA",
      "action": "BUY",
      "price": 5.1,
      "qty": 39200,
      "sources": [
        "red"
      ]
    }
  ],
  "blue": {
    "cash": 1013725.0,
    "positions": {
      "KCE": {
        "qty": 5700,
        "avg_price": 34.75,
        "value": 198075.0,
        "time": "2026-05-26 10:20"
      }
    }
  },
  "red": {
    "cash": 1029630.0,
    "positions": {
      "WHA": {
        "qty": 39200,
        "avg_price": 5.1,
        "value": 199920.0,
        "time": "2026-05-26 11:05"
      }
    }
  }
}