[
  {
    "sector_code": "AGRO- เกษตรและอุตสาหกรรมอาหาร",
    "sector_name": "",
    "last": 309.32,
    "change": 0.0,
    "percent_change": 0.0,
    "volume_shares": 0,
    "value_thousand_baht": 0.0
  },
  {
    "sector_code": "AGRI- ธุรกิจการเกษตร",
    "sector_name": "",
    "last": 207.4,
    "change": 0.0,
    "percent_change": 0.0,
    "volume_shares": 0,
    "value_thousand_baht": 0.0
  },
  {
    "sector_code": "FOOD- อาหารและเครื่องดื่ม",
    "sector_name": "",
    "last": 8564.93,
    "change": 0.0,
    "percent_change": 0.0,
    "volume_shares": 0,
    "value_thousand_baht": 0.0
  },
  {
    "sector_code": "CONSUMP- สินค้าอุปโภคบริโภค",
    "sector_name": "",
    "last": 45.23,
    "change": 0.0,
    "percent_change": 0.0,
    "volume_shares": 0,
    "value_thousand_baht": 0.0
  },
  {
    "sector_code": "FASHION- แฟชั่น",
    "sector_name": "",
    "last": 494.44,
    "change": 0.0,
    "percent_change": 0.0,
    "volume_shares": 0,
    "value_thousand_baht": 0.0
  },
  {
    "sector_code": "HOME- ของใช้ในครัวเรือนและสำนักงาน",
    "sector_name": "",
    "last": 15.38,
    "change": 0.0,
    "percent_change": 0.0,
    "volume_shares": 0,
    "value_thousand_baht": 0.0
  },
  {
    "sector_code": "PERSON- ของใช้ส่วนตัวและเวชภัณฑ์",
    "sector_name": "",
    "last": 77.67,
    "change": 0.0,
    "percent_change": 0.0,
    "volume_shares": 0,
    "value_thousand_baht": 0.0
  },
  {
    "sector_code": "FINCIAL- ธุรกิจการเงิน",
    "sector_name": "",
    "last": 157.7,
    "change": 0.0,
    "percent_change": 0.0,
    "volume_shares": 0,
    "value_thousand_baht": 0.0
  },
  {
    "sector_code": "BANK- ธนาคาร",
    "sector_name": "",
    "last": 506.26,
    "change": 0.0,
    "percent_change": 0.0,
    "volume_shares": 0,
    "value_thousand_baht": 0.0
  },
  {
    "sector_code": "FIN- เงินทุนและหลักทรัพย์",
    "sector_name": "",
    "last": 1895.28,
    "change": 0.0,
    "percent_change": 0.0,
    "volume_shares": 0,
    "value_thousand_baht": 0.0
  },
  {
    "sector_code": "INSUR- ประกันภัยและประกันชีวิต",
    "sector_name": "",
    "last": 9412.5,
    "change": 0.0,
    "percent_change": 0.0,
    "volume_shares": 0,
    "value_thousand_baht": 0.0
  },
  {
    "sector_code": "INDUS- สินค้าอุตสาหกรรม",
    "sector_name": "",
    "last": 66.63,
    "change": 0.0,
    "percent_change": 0.0,
    "volume_shares": 0,
    "value_thousand_baht": 0.0
  },
  {
    "sector_code": "AUTO- ยานยนต์",
    "sector_name": "",
    "last": 308.01,
    "change": 0.0,
    "percent_change": 0.0,
    "volume_shares": 0,
    "value_thousand_baht": 0.0
  },
  {
    "sector_code": "IMM- วัสดุอุตสาหกรรมและเครื่องจักร",
    "sector_name": "",
    "last": 19.0,
    "change": 0.0,
    "percent_change": 0.0,
    "volume_shares": 0,
    "value_thousand_baht": 0.0
  },
  {
    "sector_code": "PAPER- กระดาษและวัสดุการพิมพ์",
    "sector_name": "",
    "last": 2180.18,
    "change": 0.0,
    "percent_change": 0.0,
    "volume_shares": 0,
    "value_thousand_baht": 0.0
  },
  {
    "sector_code": "PETRO- ปิโตรเคมีและเคมีภัณฑ์",
    "sector_name": "",
    "last": 684.58,
    "change": 0.0,
    "percent_change": 0.0,
    "volume_shares": 0,
    "value_thousand_baht": 0.0
  },
  {
    "sector_code": "PKG- บรรจุภัณฑ์",
    "sector_name": "",
    "last": 2560.83,
    "change": 0.0,
    "percent_change": 0.0,
    "volume_shares": 0,
    "value_thousand_baht": 0.0
  },
  {
    "sector_code": "STEEL- เหล็ก และ ผลิตภัณฑ์โลหะ",
    "sector_name": "",
    "last": 19.8,
    "change": 0.0,
    "percent_change": 0.0,
    "volume_shares": 0,
    "value_thousand_baht": 0.0
  },
  {
    "sector_code": "PROPCON- อสังหาริมทรัพย์และก่อสร้าง",
    "sector_name": "",
    "last": 76.06,
    "change": 0.0,
    "percent_change": 0.0,
    "volume_shares": 0,
    "value_thousand_baht": 0.0
  },
  {
    "sector_code": "CONMAT- วัสดุก่อสร้าง",
    "sector_name": "",
    "last": 5631.29,
    "change": 0.0,
    "percent_change": 0.0,
    "volume_shares": 0,
    "value_thousand_baht": 0.0
  },
  {
    "sector_code": "PROP- พัฒนาอสังหาริมทรัพย์",
    "sector_name": "",
    "last": 166.81,
    "change": 0.0,
    "percent_change": 0.0,
    "volume_shares": 0,
    "value_thousand_baht": 0.0
  },
  {
    "sector_code": "PF&REIT- กองทุนรวมอสังหาริมทรัพย์และกองทรัสต์เพื่อการลงทุนในอสังหาริมทรัพย์",
    "sector_name": "",
    "last": 137.02,
    "change": 0.0,
    "percent_change": 0.0,
    "volume_shares": 0,
    "value_thousand_baht": 0.0
  },
  {
    "sector_code": "CONS- บริการรับเหมาก่อสร้าง",
    "sector_name": "",
    "last": 41.21,
    "change": 0.0,
    "percent_change": 0.0,
    "volume_shares": 0,
    "value_thousand_baht": 0.0
  },
  {
    "sector_code": "RESOURC- ทรัพยากร",
    "sector_name": "",
    "last": 171.52,
    "change": 0.0,
    "percent_change": 0.0,
    "volume_shares": 0,
    "value_thousand_baht": 0.0
  },
  {
    "sector_code": "ENERG- พลังงานและสาธารณูปโภค",
    "sector_name": "",
    "last": 19563.58,
    "change": 0.0,
    "percent_change": 0.0,
    "volume_shares": 0,
    "value_thousand_baht": 0.0
  },
  {
    "sector_code": "MINE- เหมืองแร่",
    "sector_name": "",
    "last": 4.78,
    "change": 0.0,
    "percent_change": 0.0,
    "volume_shares": 0,
    "value_thousand_baht": 0.0
  },
  {
    "sector_code": "SERVICE- บริการ",
    "sector_name": "",
    "last": 278.58,
    "change": 0.0,
    "percent_change": 0.0,
    "volume_shares": 0,
    "value_thousand_baht": 0.0
  },
  {
    "sector_code": "COMM- พาณิชย์",
    "sector_name": "",
    "last": 20189.05,
    "change": 0.0,
    "percent_change": 0.0,
    "volume_shares": 0,
    "value_thousand_baht": 0.0
  },
  {
    "sector_code": "HELTH- การแพทย์",
    "sector_name": "",
    "last": 4138.01,
    "change": 0.0,
    "percent_change": 0.0,
    "volume_shares": 0,
    "value_thousand_baht": 0.0
  },
  {
    "sector_code": "MEDIA- สื่อและสิ่งพิมพ์",
    "sector_name": "",
    "last": 15.16,
    "change": 0.0,
    "percent_change": 0.0,
    "volume_shares": 0,
    "value_thousand_baht": 0.0
  },
  {
    "sector_code": "PROF- บริการเฉพาะกิจ",
    "sector_name": "",
    "last": 133.27,
    "change": 0.0,
    "percent_change": 0.0,
    "volume_shares": 0,
    "value_thousand_baht": 0.0
  },
  {
    "sector_code": "TOURISM- การท่องเที่ยวและสันทนาการ",
    "sector_name": "",
    "last": 405.75,
    "change": 0.0,
    "percent_change": 0.0,
    "volume_shares": 0,
    "value_thousand_baht": 0.0
  },
  {
    "sector_code": "TRANS- ขนส่งและโลจิสติกส์",
    "sector_name": "",
    "last": 209.37,
    "change": 0.0,
    "percent_change": 0.0,
    "volume_shares": 0,
    "value_thousand_baht": 0.0
  },
  {
    "sector_code": "TECH- เทคโนโลยี",
    "sector_name": "",
    "last": 665.41,
    "change": 0.0,
    "percent_change": 0.0,
    "volume_shares": 0,
    "value_thousand_baht": 0.0
  },
  {
    "sector_code": "ETRON- ชิ้นส่วนอิเล็กทรอนิกส์",
    "sector_name": "",
    "last": 36053.76,
    "change": 0.0,
    "percent_change": 0.0,
    "volume_shares": 0,
    "value_thousand_baht": 0.0
  },
  {
    "sector_code": "ICT- เทคโนโลยีสารสนเทศและการสื่อสาร",
    "sector_name": "",
    "last": 231.52,
    "change": 0.0,
    "percent_change": 0.0,
    "volume_shares": 0,
    "value_thousand_baht": 0.0
  }
]